light_show_manager-1.0.0.dist-info/licenses/LICENSE
lightshow/__init__.py
lightshow/device_state.py
lightshow/exceptions.py
lightshow/executor.py
lightshow/logger.py
lightshow/logging_bridge.py
lightshow/manager.py
lightshow/notifications.py
lightshow/process_lock.py
lightshow/rotation.py
lightshow/show.py
lightshow/timeline.py
lightshow/utils.py
lightshow/volume_scheduler.py
lightshow/audio/__init__.py
lightshow/audio/afplay_backend.py
lightshow/audio/audio_player.py
lightshow/audio/exceptions.py
light_show_manager-1.0.0.dist-info/METADATA
light_show_manager-1.0.0.dist-info/WHEEL
light_show_manager-1.0.0.dist-info/top_level.txt
light_show_manager-1.0.0.dist-info/RECORD
