Metadata-Version: 2.4
Name: light-show-manager
Version: 1.0.0
Summary: Timeline-based show orchestration framework for coordinating time-synchronized commands
Author: Jimmy Hickman
License: MIT
Project-URL: Homepage, https://github.com/JimmyJammed/light-show-manager
Project-URL: Documentation, https://github.com/JimmyJammed/light-show-manager#readme
Project-URL: Repository, https://github.com/JimmyJammed/light-show-manager
Project-URL: Bug Tracker, https://github.com/JimmyJammed/light-show-manager/issues
Keywords: light-show,timeline,orchestration,automation,show-control
Classifier: Development Status :: 4 - Beta
Classifier: Intended Audience :: Developers
Classifier: License :: OSI Approved :: MIT License
Classifier: Programming Language :: Python :: 3
Classifier: Programming Language :: Python :: 3.8
Classifier: Programming Language :: Python :: 3.9
Classifier: Programming Language :: Python :: 3.10
Classifier: Programming Language :: Python :: 3.11
Classifier: Programming Language :: Python :: 3.12
Classifier: Topic :: Software Development :: Libraries :: Python Modules
Classifier: Topic :: Multimedia :: Sound/Audio
Classifier: Topic :: System :: Hardware
Requires-Python: >=3.8
License-File: LICENSE
Provides-Extra: audio
Requires-Dist: pygame>=2.5.0; extra == "audio"
Provides-Extra: dev
Requires-Dist: pytest>=7.4.0; extra == "dev"
Requires-Dist: pytest-asyncio>=0.21.0; extra == "dev"
Requires-Dist: pytest-cov>=4.1.0; extra == "dev"
Requires-Dist: black>=23.7.0; extra == "dev"
Requires-Dist: ruff>=0.0.280; extra == "dev"
Requires-Dist: mypy>=1.4.0; extra == "dev"
Provides-Extra: all
Requires-Dist: pygame>=2.5.0; extra == "all"
Dynamic: license-file
